function_registry/__init__.py
function_registry/base.py
function_registry/enums.py
function_registry/exceptions.py
function_registry/registry.py
function_registry/types.py
function_registry-1.0.0.dist-info/LICENSE
function_registry-1.0.0.dist-info/METADATA
function_registry-1.0.0.dist-info/WHEEL
function_registry-1.0.0.dist-info/top_level.txt
function_registry-1.0.0.dist-info/RECORD
