Metadata-Version: 2.1
Name: function_registry
Version: 1.0.0
Summary: Tool to consolidate python functions with multiple versions into a single access point, search by a specific version or custom search with metadata.
Home-page: https://github.com/sgg10/function-registry/
Author: sgg10
Author-email: sgg10.develop@gmail.com
License: MIT
Project-URL: Bug Reports, https://github.com/sgg10/function-registry/issues
Project-URL: Source, https://github.com/sgg10/function-registry/
Project-URL: Repository, https://github.com/sgg10/function-registry/
Classifier: Development Status :: 3 - Alpha
Classifier: Topic :: Utilities
Classifier: License :: OSI Approved :: MIT License
Classifier: Programming Language :: Python :: 3
Classifier: Programming Language :: Python :: 3.9
Requires-Python: >=3.9
License-File: LICENSE
